Workbook

Sheet Assumptions
A1: NIKE, INC. — 3-STATEMENT FINANCIAL MODEL
A2: Key Assumptions | $ in millions except % and days
A3: Legend: blue = hardcoded input/override; black = formula or historical reference. Forecast assumptions (FY2026E-FY2030E) are held flat across the projection period for simplicity, except where noted.
B5: FY2023A | C5: FY2024A | D5: FY2025A | E5: FY2026E | F5: FY2027E | G5: FY2028E | H5: FY2029E | I5: FY2030E
A6: Income Statement & Capex Drivers
A7: Revenue growth (% YoY) | C7: ='Income Statement'!C5/'Income Statement'!B5-1 -> 0.0028310912 | D7: ='Income Statement'!D5/'Income Statement'!C5-1 -> -0.098380125 | E7: 0.03 | F7: 0.03 | G7: 0.03 | H7: 0.03 | I7: 0.03
A8: COGS (% of revenue) | B8: ='Income Statement'!B6/'Income Statement'!B5 -> 0.56475389 | C8: ='Income Statement'!C6/'Income Statement'!C5 -> 0.55315214 | D8: ='Income Statement'!D6/'Income Statement'!D5 -> 0.57265326 | E8: =AVERAGE($B8:$D8) -> 0.56351976 | F8: =AVERAGE($B8:$D8) -> 0.56351976 | G8: =AVERAGE($B8:$D8) -> 0.56351976 | H8: =AVERAGE($B8:$D8) -> 0.56351976 | I8: =AVERAGE($B8:$D8) -> 0.56351976
A9: SG&A (% of revenue) | B9: ='Income Statement'!B8/'Income Statement'!B5 -> 0.31975711 | C9: ='Income Statement'!C8/'Income Statement'!C5 -> 0.31534987 | D9: ='Income Statement'!D8/'Income Statement'!D5 -> 0.34740547 | E9: =AVERAGE($B9:$D9) -> 0.32750415 | F9: =AVERAGE($B9:$D9) -> 0.32750415 | G9: =AVERAGE($B9:$D9) -> 0.32750415 | H9: =AVERAGE($B9:$D9) -> 0.32750415 | I9: =AVERAGE($B9:$D9) -> 0.32750415
A10: D&A (% of revenue) | B10: ='Supporting Schedules'!B8/'Income Statement'!B5 -> 0.013725911 | C10: ='Supporting Schedules'!C8/'Income Statement'!C5 -> 0.015497839 | D10: ='Supporting Schedules'!D8/'Income Statement'!D5 -> 0.016735408 | E10: =AVERAGE($B10:$D10) -> 0.015319719 | F10: =AVERAGE($B10:$D10) -> 0.015319719 | G10: =AVERAGE($B10:$D10) -> 0.015319719 | H10: =AVERAGE($B10:$D10) -> 0.015319719 | I10: =AVERAGE($B10:$D10) -> 0.015319719
A11: Capex (% of revenue) | B11: ='Supporting Schedules'!B7/'Income Statement'!B5 -> 0.018919499 | C11: ='Supporting Schedules'!C7/'Income Statement'!C5 -> 0.015809353 | D11: ='Supporting Schedules'!D7/'Income Statement'!D5 -> 0.0092854521 | E11: =AVERAGE($B11:$D11) -> 0.014671435 | F11: =AVERAGE($B11:$D11) -> 0.014671435 | G11: =AVERAGE($B11:$D11) -> 0.014671435 | H11: =AVERAGE($B11:$D11) -> 0.014671435 | I11: =AVERAGE($B11:$D11) -> 0.014671435
A12: Non-operating income (net), $mm | B12: ='Income Statement'!B10 -> 286 | C12: ='Income Statement'!C10 -> -51 | D12: ='Income Statement'!D10 -> 183 | E12: =AVERAGE($B12:$D12) -> 139.33333 | F12: =AVERAGE($B12:$D12) -> 139.33333 | G12: =AVERAGE($B12:$D12) -> 139.33333 | H12: =AVERAGE($B12:$D12) -> 139.33333 | I12: =AVERAGE($B12:$D12) -> 139.33333
A13: Effective tax rate (%) | B13: ='Income Statement'!B12/'Income Statement'!B11 -> 0.18238994 | C13: ='Income Statement'!C12/'Income Statement'!C11 -> 0.14963449 | D13: ='Income Statement'!D12/'Income Statement'!D11 -> 0.17142857 | E13: =AVERAGE($B13:$D13) -> 0.16781767 | F13: =AVERAGE($B13:$D13) -> 0.16781767 | G13: =AVERAGE($B13:$D13) -> 0.16781767 | H13: =AVERAGE($B13:$D13) -> 0.16781767 | I13: =AVERAGE($B13:$D13) -> 0.16781767
A14: Stock-based compensation, $mm | B14: ='Cash Flow Statement'!B8 -> 755 | C14: ='Cash Flow Statement'!C8 -> 804 | D14: ='Cash Flow Statement'!D8 -> 709 | E14: =AVERAGE($B14:$D14) -> 756 | F14: =AVERAGE($B14:$D14) -> 756 | G14: =AVERAGE($B14:$D14) -> 756 | H14: =AVERAGE($B14:$D14) -> 756 | I14: =AVERAGE($B14:$D14) -> 756
A16: Working Capital Drivers
A17: Accounts receivable days | B17: ='Balance Sheet'!B8/'Income Statement'!B5*365 -> 29.439737 | C17: ='Balance Sheet'!C8/'Income Statement'!C5*365 -> 31.460126 | D17: ='Balance Sheet'!D8/'Income Statement'!D5*365 -> 37.178626 | E17: =AVERAGE($B17:$D17) -> 32.69283 | F17: =AVERAGE($B17:$D17) -> 32.69283 | G17: =AVERAGE($B17:$D17) -> 32.69283 | H17: =AVERAGE($B17:$D17) -> 32.69283 | I17: =AVERAGE($B17:$D17) -> 32.69283
A18: Inventory days | B18: ='Balance Sheet'!B9/'Income Statement'!B6*365 -> 106.67969 | C18: ='Balance Sheet'!C9/'Income Statement'!C6*365 -> 96.597621 | D18: ='Balance Sheet'!D9/'Income Statement'!D6*365 -> 103.07647 | E18: =AVERAGE($B18:$D18) -> 102.11793 | F18: =AVERAGE($B18:$D18) -> 102.11793 | G18: =AVERAGE($B18:$D18) -> 102.11793 | H18: =AVERAGE($B18:$D18) -> 102.11793 | I18: =AVERAGE($B18:$D18) -> 102.11793
A19: Accounts payable days | B19: ='Balance Sheet'!B22/'Income Statement'!B6*365 -> 36.115125 | C19: ='Balance Sheet'!C22/'Income Statement'!C6*365 -> 36.627187 | D19: ='Balance Sheet'!D22/'Income Statement'!D6*365 -> 47.88397 | E19: =AVERAGE($B19:$D19) -> 40.208761 | F19: =AVERAGE($B19:$D19) -> 40.208761 | G19: =AVERAGE($B19:$D19) -> 40.208761 | H19: =AVERAGE($B19:$D19) -> 40.208761 | I19: =AVERAGE($B19:$D19) -> 40.208761
A21: Capital Structure & Distribution Assumptions
A22: Dividend payout ratio (% of net income) | B22: =-'Cash Flow Statement'!B23/'Income Statement'!B13 -> 0.39684418 | C22: =-'Cash Flow Statement'!C23/'Income Statement'!C13 -> 0.38052632 | D22: =-'Cash Flow Statement'!D23/'Income Statement'!D13 -> 0.71450761 | E22: 0.4 | F22: 0.4 | G22: 0.4 | H22: 0.4 | I22: 0.4
A23: Share repurchases, $mm | B23: =-'Cash Flow Statement'!B24 -> 5480 | C23: =-'Cash Flow Statement'!C24 -> 4250 | D23: =-'Cash Flow Statement'!D24 -> 2985 | E23: 0 | F23: 0 | G23: 0 | H23: 0 | I23: 0
A24: Net debt issuance / (repayment), $mm | B24: ='Cash Flow Statement'!B22 -> -504 | C24: ='Cash Flow Statement'!C22 -> 0 | D24: ='Cash Flow Statement'!D22 -> -1000 | E24: 0 | F24: 0 | G24: 0 | H24: 0 | I24: 0
A26: Overrides vs. 3-yr historical average: dividend payout set to 40% (vs. ~50% historical, which is skewed by FY2025's depressed net income); share buybacks and net debt activity assumed at zero (discontinued) for forecast simplicity.

Sheet Income Statement
A1: NIKE, INC. — INCOME STATEMENT
A2: $ in millions | Fiscal year ended May 31
B4: FY2023A | C4: FY2024A | D4: FY2025A | E4: FY2026E | F4: FY2027E | G4: FY2028E | H4: FY2029E | I4: FY2030E
A5: Revenue | B5: 51217 | C5: 51362 | D5: 46309 | E5: =D5*(1+Assumptions!E7) -> 47698.27 | F5: =E5*(1+Assumptions!F7) -> 49129.218 | G5: =F5*(1+Assumptions!G7) -> 50603.095 | H5: =G5*(1+Assumptions!H7) -> 52121.187 | I5: =H5*(1+Assumptions!I7) -> 53684.823
A6: Cost of goods sold | B6: 28925 | C6: 28411 | D6: 26519 | E6: =E5*Assumptions!E8 -> 26878.918 | F6: =F5*Assumptions!F8 -> 27685.285 | G6: =G5*Assumptions!G8 -> 28515.844 | H6: =H5*Assumptions!H8 -> 29371.319 | I6: =I5*Assumptions!I8 -> 30252.459
A7: Gross profit | B7: =B5-B6 -> 22292 | C7: =C5-C6 -> 22951 | D7: =D5-D6 -> 19790 | E7: =E5-E6 -> 20819.352 | F7: =F5-F6 -> 21443.933 | G7: =G5-G6 -> 22087.251 | H7: =H5-H6 -> 22749.868 | I7: =I5-I6 -> 23432.364
A8: Selling, general & administrative | B8: 16377 | C8: 16197 | D8: 16088 | E8: =E5*Assumptions!E9 -> 15621.381 | F8: =F5*Assumptions!F9 -> 16090.023 | G8: =G5*Assumptions!G9 -> 16572.724 | H8: =H5*Assumptions!H9 -> 17069.905 | I8: =I5*Assumptions!I9 -> 17582.002
A9: Operating income (EBIT) | B9: =B7-B8 -> 5915 | C9: =C7-C8 -> 6754 | D9: =D7-D8 -> 3702 | E9: =E7-E8 -> 5197.9708 | F9: =F7-F8 -> 5353.9099 | G9: =G7-G8 -> 5514.5272 | H9: =H7-H8 -> 5679.963 | I9: =I7-I8 -> 5850.3619
A10: Non-operating income (net) | B10: 286 | C10: -51 | D10: 183 | E10: =Assumptions!E12 -> 139.33333 | F10: =Assumptions!F12 -> 139.33333 | G10: =Assumptions!G12 -> 139.33333 | H10: =Assumptions!H12 -> 139.33333 | I10: =Assumptions!I12 -> 139.33333
A11: Pretax income | B11: =B9+B10 -> 6201 | C11: =C9+C10 -> 6703 | D11: =D9+D10 -> 3885 | E11: =E9+E10 -> 5337.3041 | F11: =F9+F10 -> 5493.2432 | G11: =G9+G10 -> 5653.8605 | H11: =H9+H10 -> 5819.2963 | I11: =I9+I10 -> 5989.6952
A12: Income tax expense | B12: 1131 | C12: 1003 | D12: 666 | E12: =E11*Assumptions!E13 -> 895.69392 | F12: =F11*Assumptions!F13 -> 921.86326 | G12: =G11*Assumptions!G13 -> 948.81768 | H12: =H11*Assumptions!H13 -> 976.58073 | I12: =I11*Assumptions!I13 -> 1005.1767
A13: Net income | B13: =B11-B12 -> 5070 | C13: =C11-C12 -> 5700 | D13: =D11-D12 -> 3219 | E13: =E11-E12 -> 4441.6102 | F13: =F11-F12 -> 4571.3799 | G13: =G11-G12 -> 4705.0428 | H13: =H11-H12 -> 4842.7156 | I13: =I11-I12 -> 4984.5185
A15: Gross margin % | B15: =B7/B5 -> 0.43524611 | C15: =C7/C5 -> 0.44684786 | D15: =D7/D5 -> 0.42734674 | E15: =E7/E5 -> 0.43648024 | F15: =F7/F5 -> 0.43648024 | G15: =G7/G5 -> 0.43648024 | H15: =H7/H5 -> 0.43648024 | I15: =I7/I5 -> 0.43648024
A16: Operating margin % | B16: =B9/B5 -> 0.115489 | C16: =C9/C5 -> 0.13149799 | D16: =D9/D5 -> 0.079941264 | E16: =E9/E5 -> 0.10897609 | F16: =F9/F5 -> 0.10897609 | G16: =G9/G5 -> 0.10897609 | H16: =H9/H5 -> 0.10897609 | I16: =I9/I5 -> 0.10897609
A17: Net margin % | B17: =B13/B5 -> 0.09899057 | C17: =C13/C5 -> 0.11097699 | D17: =D13/D5 -> 0.069511326 | E17: =E13/E5 -> 0.093118894 | F17: =F13/F5 -> 0.093048091 | G17: =G13/G5 -> 0.09297935 | H17: =H13/H5 -> 0.09291261 | I17: =I13/I5 -> 0.092847815
A18: Revenue growth % YoY | C18: =C5/B5-1 -> 0.0028310912 | D18: =D5/C5-1 -> -0.098380125 | E18: =E5/D5-1 -> 0.03 | F18: =F5/E5-1 -> 0.03 | G18: =G5/F5-1 -> 0.03 | H18: =H5/G5-1 -> 0.03 | I18: =I5/H5-1 -> 0.03
A20: Sources: NIKE, Inc. Form 10-K, FY2025 (filed with SEC, period ended May 31, 2025) and FY2024 10-K (period ended May 31, 2024), Consolidated Statements of Income. SEC EDGAR CIK 0000320187.

Sheet Balance Sheet
A1: NIKE, INC. — BALANCE SHEET
A2: $ in millions | As of May 31
B4: FY2023A | C4: FY2024A | D4: FY2025A | E4: FY2026E | F4: FY2027E | G4: FY2028E | H4: FY2029E | I4: FY2030E
A5: ASSETS
A6: Cash and equivalents | B6: 7441 | C6: 9860 | D6: 7464 | E6: ='Cash Flow Statement'!E31 -> 10811.538 | F6: ='Cash Flow Statement'!F31 -> 14077.275 | G6: ='Cash Flow Statement'!G31 -> 17416.217 | H6: ='Cash Flow Statement'!H31 -> 20830.561 | I6: ='Cash Flow Statement'!I31 -> 24322.567
A7: Short-term investments | B7: 3234 | C7: 1722 | D7: 1687 | E7: =D7 -> 1687 | F7: =E7 -> 1687 | G7: =F7 -> 1687 | H7: =G7 -> 1687 | I7: =H7 -> 1687
A8: Accounts receivable, net | B8: 4131 | C8: 4427 | D8: 4717 | E8: ='Supporting Schedules'!E13 -> 4272.3053 | F8: ='Supporting Schedules'!F13 -> 4400.4744 | G8: ='Supporting Schedules'!G13 -> 4532.4886 | H8: ='Supporting Schedules'!H13 -> 4668.4633 | I8: ='Supporting Schedules'!I13 -> 4808.5172
A9: Inventories | B9: 8454 | C9: 7519 | D9: 7489 | E9: ='Supporting Schedules'!E14 -> 7520.0531 | F9: ='Supporting Schedules'!F14 -> 7745.6547 | G9: ='Supporting Schedules'!G14 -> 7978.0243 | H9: ='Supporting Schedules'!H14 -> 8217.3651 | I9: ='Supporting Schedules'!I14 -> 8463.886
A10: Prepaid expenses & other current assets | B10: 1942 | C10: 1854 | D10: 2005 | E10: =D10 -> 2005 | F10: =E10 -> 2005 | G10: =F10 -> 2005 | H10: =G10 -> 2005 | I10: =H10 -> 2005
A11: Total current assets | B11: =SUM(B6:B10) -> 25202 | C11: =SUM(C6:C10) -> 25382 | D11: =SUM(D6:D10) -> 23362 | E11: =SUM(E6:E10) -> 26295.896 | F11: =SUM(F6:F10) -> 29915.404 | G11: =SUM(G6:G10) -> 33618.73 | H11: =SUM(H6:H10) -> 37408.389 | I11: =SUM(I6:I10) -> 41286.97
A12: Property, plant & equipment, net | B12: 5081 | C12: 5000 | D12: 4828 | E12: ='Supporting Schedules'!E10 -> 4797.078 | F12: ='Supporting Schedules'!F10 -> 4765.2282 | G12: ='Supporting Schedules'!G10 -> 4732.423 | H12: ='Supporting Schedules'!H10 -> 4698.6337 | I12: ='Supporting Schedules'!I10 -> 4663.8307
A13: Operating lease right-of-use assets, net | B13: 2923 | C13: 2718 | D13: 2712 | E13: =D13 -> 2712 | F13: =E13 -> 2712 | G13: =F13 -> 2712 | H13: =G13 -> 2712 | I13: =H13 -> 2712
A14: Identifiable intangible assets, net | B14: 274 | C14: 259 | D14: 259 | E14: =D14 -> 259 | F14: =E14 -> 259 | G14: =F14 -> 259 | H14: =G14 -> 259 | I14: =H14 -> 259
A15: Goodwill | B15: 281 | C15: 240 | D15: 240 | E15: =D15 -> 240 | F15: =E15 -> 240 | G15: =F15 -> 240 | H15: =G15 -> 240 | I15: =H15 -> 240
A16: Deferred income taxes & other assets | B16: 3770 | C16: 4511 | D16: 5178 | E16: =D16 -> 5178 | F16: =E16 -> 5178 | G16: =F16 -> 5178 | H16: =G16 -> 5178 | I16: =H16 -> 5178
A17: TOTAL ASSETS | B17: =B11+B12+B13+B14+B15+B16 -> 37531 | C17: =C11+C12+C13+C14+C15+C16 -> 38110 | D17: =D11+D12+D13+D14+D15+D16 -> 36579 | E17: =E11+E12+E13+E14+E15+E16 -> 39481.974 | F17: =F11+F12+F13+F14+F15+F16 -> 43069.632 | G17: =G11+G12+G13+G14+G15+G16 -> 46740.153 | H17: =H11+H12+H13+H14+H15+H16 -> 50496.023 | I17: =I11+I12+I13+I14+I15+I16 -> 54339.801
A19: LIABILITIES
A20: Current portion of long-term debt | B20: 0 | C20: 1000 | D20: 0 | E20: =D20 -> 0 | F20: =E20 -> 0 | G20: =F20 -> 0 | H20: =G20 -> 0 | I20: =H20 -> 0
A21: Notes payable | B21: 6 | C21: 6 | D21: 5 | E21: =D21 -> 5 | F21: =E21 -> 5 | G21: =F21 -> 5 | H21: =G21 -> 5 | I21: =H21 -> 5
A22: Accounts payable | B22: 2862 | C22: 2851 | D22: 3479 | E22: ='Supporting Schedules'!E15 -> 2961.0081 | F22: ='Supporting Schedules'!F15 -> 3049.8384 | G22: ='Supporting Schedules'!G15 -> 3141.3335 | H22: ='Supporting Schedules'!H15 -> 3235.5735 | I22: ='Supporting Schedules'!I15 -> 3332.6408
A23: Current portion of operating lease liabilities | B23: 425 | C23: 477 | D23: 502 | E23: =D23 -> 502 | F23: =E23 -> 502 | G23: =F23 -> 502 | H23: =G23 -> 502 | I23: =H23 -> 502
A24: Accrued liabilities | B24: 5723 | C24: 5725 | D24: 5911 | E24: =D24 -> 5911 | F24: =E24 -> 5911 | G24: =F24 -> 5911 | H24: =G24 -> 5911 | I24: =H24 -> 5911
A25: Income taxes payable | B25: 240 | C25: 534 | D25: 669 | E25: =D25 -> 669 | F25: =E25 -> 669 | G25: =F25 -> 669 | H25: =G25 -> 669 | I25: =H25 -> 669
A26: Total current liabilities | B26: =SUM(B20:B25) -> 9256 | C26: =SUM(C20:C25) -> 10593 | D26: =SUM(D20:D25) -> 10566 | E26: =SUM(E20:E25) -> 10048.008 | F26: =SUM(F20:F25) -> 10136.838 | G26: =SUM(G20:G25) -> 10228.334 | H26: =SUM(H20:H25) -> 10322.574 | I26: =SUM(I20:I25) -> 10419.641
A27: Long-term debt | B27: 8927 | C27: 7903 | D27: 7961 | E27: ='Supporting Schedules'!E20 -> 7961 | F27: ='Supporting Schedules'!F20 -> 7961 | G27: ='Supporting Schedules'!G20 -> 7961 | H27: ='Supporting Schedules'!H20 -> 7961 | I27: ='Supporting Schedules'!I20 -> 7961
A28: Operating lease liabilities | B28: 2786 | C28: 2566 | D28: 2550 | E28: =D28 -> 2550 | F28: =E28 -> 2550 | G28: =F28 -> 2550 | H28: =G28 -> 2550 | I28: =H28 -> 2550
A29: Deferred income taxes & other liabilities | B29: 2558 | C29: 2618 | D29: 2289 | E29: =D29 -> 2289 | F29: =E29 -> 2289 | G29: =F29 -> 2289 | H29: =G29 -> 2289 | I29: =H29 -> 2289
A30: TOTAL LIABILITIES | B30: =B26+B27+B28+B29 -> 23527 | C30: =C26+C27+C28+C29 -> 23680 | D30: =D26+D27+D28+D29 -> 23366 | E30: =E26+E27+E28+E29 -> 22848.008 | F30: =F26+F27+F28+F29 -> 22936.838 | G30: =G26+G27+G28+G29 -> 23028.334 | H30: =H26+H27+H28+H29 -> 23122.574 | I30: =I26+I27+I28+I29 -> 23219.641
A32: SHAREHOLDERS' EQUITY
A33: Common stock | B33: 3 | C33: 3 | D33: 3 | E33: =D33 -> 3 | F33: =E33 -> 3 | G33: =F33 -> 3 | H33: =G33 -> 3 | I33: =H33 -> 3
A34: Capital in excess of stated value (APIC) | B34: 12412 | C34: 13409 | D34: 14195 | E34: =D34+'Cash Flow Statement'!E8 -> 14951 | F34: =E34+'Cash Flow Statement'!F8 -> 15707 | G34: =F34+'Cash Flow Statement'!G8 -> 16463 | H34: =G34+'Cash Flow Statement'!H8 -> 17219 | I34: =H34+'Cash Flow Statement'!I8 -> 17975
A35: Accumulated other comprehensive income (loss) | B35: 231 | C35: 53 | D35: -258 | E35: =D35 -> -258 | F35: =E35 -> -258 | G35: =F35 -> -258 | H35: =G35 -> -258 | I35: =H35 -> -258
A36: Retained earnings (deficit) | B36: 1358 | C36: 965 | D36: -727 | E36: =D36+'Income Statement'!E13+'Cash Flow Statement'!E23+'Cash Flow Statement'!E24 -> 1937.9661 | F36: =E36+'Income Statement'!F13+'Cash Flow Statement'!F23+'Cash Flow Statement'!F24 -> 4680.7941 | G36: =F36+'Income Statement'!G13+'Cash Flow Statement'!G23+'Cash Flow Statement'!G24 -> 7503.8198 | H36: =G36+'Income Statement'!H13+'Cash Flow Statement'!H23+'Cash Flow Statement'!H24 -> 10409.449 | I36: =H36+'Income Statement'!I13+'Cash Flow Statement'!I23+'Cash Flow Statement'!I24 -> 13400.16
A37: TOTAL SHAREHOLDERS' EQUITY | B37: =SUM(B33:B36) -> 14004 | C37: =SUM(C33:C36) -> 14430 | D37: =SUM(D33:D36) -> 13213 | E37: =SUM(E33:E36) -> 16633.966 | F37: =SUM(F33:F36) -> 20132.794 | G37: =SUM(G33:G36) -> 23711.82 | H37: =SUM(H33:H36) -> 27373.449 | I37: =SUM(I33:I36) -> 31120.16
A39: TOTAL LIABILITIES & SHAREHOLDERS' EQUITY | B39: =B30+B37 -> 37531 | C39: =C30+C37 -> 38110 | D39: =D30+D37 -> 36579 | E39: =E30+E37 -> 39481.974 | F39: =F30+F37 -> 43069.632 | G39: =G30+G37 -> 46740.153 | H39: =H30+H37 -> 50496.023 | I39: =I30+I37 -> 54339.801
A41: Balance (should be zero) | B41: =B17-B39 -> 0 | C41: =C17-C39 -> 0 | D41: =D17-D39 -> 0 | E41: =E17-E39 -> 0 | F41: =F17-F39 -> 0 | G41: =G17-G39 -> 0 | H41: =H17-H39 -> 0 | I41: =I17-I39 -> 0
A43: Sources: NIKE, Inc. Form 10-K, FY2025 (period ended May 31, 2025) and FY2023 10-K (period ended May 31, 2023, for FY2022 comparatives used as forecast roll-forward starting points), Consolidated Balance Sheets. SEC EDGAR CIK 0000320187.

Sheet Cash Flow Statement
A1: NIKE, INC. — CASH FLOW STATEMENT
A2: $ in millions | Fiscal year ended May 31
B4: FY2023A | C4: FY2024A | D4: FY2025A | E4: FY2026E | F4: FY2027E | G4: FY2028E | H4: FY2029E | I4: FY2030E
A5: Cash flows from operating activities
A6: Net income | B6: ='Income Statement'!B13 -> 5070 | C6: ='Income Statement'!C13 -> 5700 | D6: ='Income Statement'!D13 -> 3219 | E6: ='Income Statement'!E13 -> 4441.6102 | F6: ='Income Statement'!F13 -> 4571.3799 | G6: ='Income Statement'!G13 -> 4705.0428 | H6: ='Income Statement'!H13 -> 4842.7156 | I6: ='Income Statement'!I13 -> 4984.5185
A7: Depreciation & amortization | B7: ='Supporting Schedules'!B8 -> 703 | C7: ='Supporting Schedules'!C8 -> 796 | D7: ='Supporting Schedules'!D8 -> 775 | E7: ='Supporting Schedules'!E8 -> 730.72411 | F7: ='Supporting Schedules'!F8 -> 752.64583 | G7: ='Supporting Schedules'!G8 -> 775.22521 | H7: ='Supporting Schedules'!H8 -> 798.48196 | I7: ='Supporting Schedules'!I8 -> 822.43642
A8: Stock-based compensation | B8: 755 | C8: 804 | D8: 709 | E8: =Assumptions!E14 -> 756 | F8: =Assumptions!F14 -> 756 | G8: =Assumptions!G14 -> 756 | H8: =Assumptions!H14 -> 756 | I8: =Assumptions!I14 -> 756
A9: Deferred taxes & other non-cash items | B9: -174 | C9: -587 | D9: -218 | E9: 0 | F9: 0 | G9: 0 | H9: 0 | I9: 0
A10: (Increase) / decrease in accounts receivable | B10: 489 | C10: -329 | D10: -257 | E10: =-('Balance Sheet'!E8-'Balance Sheet'!D8) -> 444.69474 | F10: =-('Balance Sheet'!F8-'Balance Sheet'!E8) -> -128.16916 | G10: =-('Balance Sheet'!G8-'Balance Sheet'!F8) -> -132.01423 | H10: =-('Balance Sheet'!H8-'Balance Sheet'!G8) -> -135.97466 | I10: =-('Balance Sheet'!I8-'Balance Sheet'!H8) -> -140.0539
A11: (Increase) / decrease in inventories | B11: -133 | C11: 908 | D11: 120 | E11: =-('Balance Sheet'!E9-'Balance Sheet'!D9) -> -31.053111 | F11: =-('Balance Sheet'!F9-'Balance Sheet'!E9) -> -225.60159 | G11: =-('Balance Sheet'!G9-'Balance Sheet'!F9) -> -232.36964 | H11: =-('Balance Sheet'!H9-'Balance Sheet'!G9) -> -239.34073 | I11: =-('Balance Sheet'!I9-'Balance Sheet'!H9) -> -246.52095
A12: Change in other working capital & non-cash items | B12: -373 | C12: 148 | D12: -1278 | E12: 0 | F12: 0 | G12: 0 | H12: 0 | I12: 0
A13: Increase / (decrease) in accounts payable | B13: -496 | C13: -11 | D13: 628 | E13: ='Balance Sheet'!E22-'Balance Sheet'!D22 -> -517.99185 | F13: ='Balance Sheet'!F22-'Balance Sheet'!E22 -> 88.830244 | G13: ='Balance Sheet'!G22-'Balance Sheet'!F22 -> 91.495152 | H13: ='Balance Sheet'!H22-'Balance Sheet'!G22 -> 94.240006 | I13: ='Balance Sheet'!I22-'Balance Sheet'!H22 -> 97.067206
A14: Cash flow from operating activities | B14: =SUM(B6:B13) -> 5841 | C14: =SUM(C6:C13) -> 7429 | D14: =SUM(D6:D13) -> 3698 | E14: =SUM(E6:E13) -> 5823.9841 | F14: =SUM(F6:F13) -> 5815.0853 | G14: =SUM(G6:G13) -> 5963.3793 | H14: =SUM(H6:H13) -> 6116.1222 | I14: =SUM(I6:I13) -> 6273.4473
A16: Cash flows from investing activities
A17: Capital expenditures | B17: =-'Supporting Schedules'!B7 -> -969 | C17: =-'Supporting Schedules'!C7 -> -812 | D17: =-'Supporting Schedules'!D7 -> -430 | E17: =-'Supporting Schedules'!E7 -> -699.80206 | F17: =-'Supporting Schedules'!F7 -> -720.79612 | G17: =-'Supporting Schedules'!G7 -> -742.42001 | H17: =-'Supporting Schedules'!H7 -> -764.69261 | I17: =-'Supporting Schedules'!I7 -> -787.63339
A18: Other investing activities, net | B18: 1533 | C18: 1706 | D18: 155 | E18: 0 | F18: 0 | G18: 0 | H18: 0 | I18: 0
A19: Cash flow from investing activities | B19: =SUM(B17:B18) -> 564 | C19: =SUM(C17:C18) -> 894 | D19: =SUM(D17:D18) -> -275 | E19: =SUM(E17:E18) -> -699.80206 | F19: =SUM(F17:F18) -> -720.79612 | G19: =SUM(G17:G18) -> -742.42001 | H19: =SUM(H17:H18) -> -764.69261 | I19: =SUM(I17:I18) -> -787.63339
A21: Cash flows from financing activities
A22: Net debt issuance / (repayment) | B22: -504 | C22: 0 | D22: -1000 | E22: =Assumptions!E24 -> 0 | F22: =Assumptions!F24 -> 0 | G22: =Assumptions!G24 -> 0 | H22: =Assumptions!H24 -> 0 | I22: =Assumptions!I24 -> 0
A23: Dividends paid | B23: -2012 | C23: -2169 | D23: -2300 | E23: =-Assumptions!E22*'Income Statement'!E13 -> -1776.6441 | F23: =-Assumptions!F22*'Income Statement'!F13 -> -1828.552 | G23: =-Assumptions!G22*'Income Statement'!G13 -> -1882.0171 | H23: =-Assumptions!H22*'Income Statement'!H13 -> -1937.0862 | I23: =-Assumptions!I22*'Income Statement'!I13 -> -1993.8074
A24: Share repurchases | B24: -5480 | C24: -4250 | D24: -2985 | E24: =-Assumptions!E23 -> 0 | F24: =-Assumptions!F23 -> 0 | G24: =-Assumptions!G23 -> 0 | H24: =-Assumptions!H23 -> 0 | I24: =-Assumptions!I23 -> 0
A25: Other financing activities, net | B25: 549 | C25: 531 | D25: 465 | E25: 0 | F25: 0 | G25: 0 | H25: 0 | I25: 0
A26: Cash flow from financing activities | B26: =SUM(B22:B25) -> -7447 | C26: =SUM(C22:C25) -> -5888 | D26: =SUM(D22:D25) -> -5820 | E26: =SUM(E22:E25) -> -1776.6441 | F26: =SUM(F22:F25) -> -1828.552 | G26: =SUM(G22:G25) -> -1882.0171 | H26: =SUM(H22:H25) -> -1937.0862 | I26: =SUM(I22:I25) -> -1993.8074
A28: Effect of exchange rate changes on cash | B28: -91 | C28: -16 | D28: 1 | E28: 0 | F28: 0 | G28: 0 | H28: 0 | I28: 0
A29: Net increase / (decrease) in cash | B29: =B14+B19+B26+B28 -> -1133 | C29: =C14+C19+C26+C28 -> 2419 | D29: =D14+D19+D26+D28 -> -2396 | E29: =E14+E19+E26+E28 -> 3347.5379 | F29: =F14+F19+F26+F28 -> 3265.7372 | G29: =G14+G19+G26+G28 -> 3338.9422 | H29: =H14+H19+H26+H28 -> 3414.3433 | I29: =I14+I19+I26+I28 -> 3492.0065
A30: Cash, beginning of period | B30: 8574 | C30: =B31 -> 7441 | D30: =C31 -> 9860 | E30: =D31 -> 7464 | F30: =E31 -> 10811.538 | G30: =F31 -> 14077.275 | H30: =G31 -> 17416.217 | I30: =H31 -> 20830.561
A31: Cash, end of period | B31: =B30+B29 -> 7441 | C31: =C30+C29 -> 9860 | D31: =D30+D29 -> 7464 | E31: =E30+E29 -> 10811.538 | F31: =F30+F29 -> 14077.275 | G31: =G30+G29 -> 17416.217 | H31: =H30+H29 -> 20830.561 | I31: =I30+I29 -> 24322.567
A32: Check vs. Balance Sheet cash (should be zero) | B32: =B31-'Balance Sheet'!B6 -> 0 | C32: =C31-'Balance Sheet'!C6 -> 0 | D32: =D31-'Balance Sheet'!D6 -> 0 | E32: =E31-'Balance Sheet'!E6 -> 0 | F32: =F31-'Balance Sheet'!F6 -> 0 | G32: =G31-'Balance Sheet'!G6 -> 0 | H32: =H31-'Balance Sheet'!H6 -> 0 | I32: =I31-'Balance Sheet'!I6 -> 0
A34: Sources: NIKE, Inc. Form 10-K, FY2025 and FY2024 (period ended May 31, 2025 and May 31, 2024), Consolidated Statements of Cash Flows; FY2022 beginning cash from FY2023 10-K comparatives. SEC EDGAR CIK 0000320187. 'Other working capital', 'other investing' and 'other financing' are aggregated 10-K line items not broken out further.

Sheet Supporting Schedules
A1: NIKE, INC. — SUPPORTING SCHEDULES
A2: $ in millions unless otherwise noted | Fiscal year ended May 31
B4: FY2023A | C4: FY2024A | D4: FY2025A | E4: FY2026E | F4: FY2027E | G4: FY2028E | H4: FY2029E | I4: FY2030E
A5: PP&E / Depreciation Schedule
A6: Beginning PP&E, net | B6: 4791 | C6: =B10 -> 5081 | D6: =C10 -> 5000 | E6: =D10 -> 4828 | F6: =E10 -> 4797.078 | G6: =F10 -> 4765.2282 | H6: =G10 -> 4732.423 | I6: =H10 -> 4698.6337
A7: (+) Capital expenditures | B7: 969 | C7: 812 | D7: 430 | E7: ='Income Statement'!E5*Assumptions!E11 -> 699.80206 | F7: ='Income Statement'!F5*Assumptions!F11 -> 720.79612 | G7: ='Income Statement'!G5*Assumptions!G11 -> 742.42001 | H7: ='Income Statement'!H5*Assumptions!H11 -> 764.69261 | I7: ='Income Statement'!I5*Assumptions!I11 -> 787.63339
A8: (-) Depreciation & amortization | B8: 703 | C8: 796 | D8: 775 | E8: ='Income Statement'!E5*Assumptions!E10 -> 730.72411 | F8: ='Income Statement'!F5*Assumptions!F10 -> 752.64583 | G8: ='Income Statement'!G5*Assumptions!G10 -> 775.22521 | H8: ='Income Statement'!H5*Assumptions!H10 -> 798.48196 | I8: ='Income Statement'!I5*Assumptions!I10 -> 822.43642
A9: (+/-) Other (FX translation, disposals, etc.) | B9: ='Balance Sheet'!B12-(B6+B7-B8) -> 24 | C9: ='Balance Sheet'!C12-(C6+C7-C8) -> -97 | D9: ='Balance Sheet'!D12-(D6+D7-D8) -> 173 | E9: 0 | F9: 0 | G9: 0 | H9: 0 | I9: 0
A10: Ending PP&E, net | B10: =B6+B7-B8+B9 -> 5081 | C10: =C6+C7-C8+C9 -> 5000 | D10: =D6+D7-D8+D9 -> 4828 | E10: =E6+E7-E8+E9 -> 4797.078 | F10: =F6+F7-F8+F9 -> 4765.2282 | G10: =G6+G7-G8+G9 -> 4732.423 | H10: =H6+H7-H8+H9 -> 4698.6337 | I10: =I6+I7-I8+I9 -> 4663.8307
A12: Working Capital Schedule
A13: Accounts receivable, $ | B13: ='Balance Sheet'!B8 -> 4131 | C13: ='Balance Sheet'!C8 -> 4427 | D13: ='Balance Sheet'!D8 -> 4717 | E13: ='Income Statement'!E5*Assumptions!E17/365 -> 4272.3053 | F13: ='Income Statement'!F5*Assumptions!F17/365 -> 4400.4744 | G13: ='Income Statement'!G5*Assumptions!G17/365 -> 4532.4886 | H13: ='Income Statement'!H5*Assumptions!H17/365 -> 4668.4633 | I13: ='Income Statement'!I5*Assumptions!I17/365 -> 4808.5172
A14: Inventories, $ | B14: ='Balance Sheet'!B9 -> 8454 | C14: ='Balance Sheet'!C9 -> 7519 | D14: ='Balance Sheet'!D9 -> 7489 | E14: ='Income Statement'!E6*Assumptions!E18/365 -> 7520.0531 | F14: ='Income Statement'!F6*Assumptions!F18/365 -> 7745.6547 | G14: ='Income Statement'!G6*Assumptions!G18/365 -> 7978.0243 | H14: ='Income Statement'!H6*Assumptions!H18/365 -> 8217.3651 | I14: ='Income Statement'!I6*Assumptions!I18/365 -> 8463.886
A15: Accounts payable, $ | B15: ='Balance Sheet'!B22 -> 2862 | C15: ='Balance Sheet'!C22 -> 2851 | D15: ='Balance Sheet'!D22 -> 3479 | E15: ='Income Statement'!E6*Assumptions!E19/365 -> 2961.0081 | F15: ='Income Statement'!F6*Assumptions!F19/365 -> 3049.8384 | G15: ='Income Statement'!G6*Assumptions!G19/365 -> 3141.3335 | H15: ='Income Statement'!H6*Assumptions!H19/365 -> 3235.5735 | I15: ='Income Statement'!I6*Assumptions!I19/365 -> 3332.6408
A17: Long-Term Debt Schedule
A18: Beginning long-term debt | B18: 8920 | C18: =B20 -> 8927 | D18: =C20 -> 7903 | E18: =D20 -> 7961 | F18: =E20 -> 7961 | G18: =F20 -> 7961 | H18: =G20 -> 7961 | I18: =H20 -> 7961
A19: Net issuance / (repayment) | B19: ='Balance Sheet'!B27-B18 -> 7 | C19: ='Balance Sheet'!C27-C18 -> -1024 | D19: ='Balance Sheet'!D27-D18 -> 58 | E19: =Assumptions!E24 -> 0 | F19: =Assumptions!F24 -> 0 | G19: =Assumptions!G24 -> 0 | H19: =Assumptions!H24 -> 0 | I19: =Assumptions!I24 -> 0
A20: Ending long-term debt | B20: =B18+B19 -> 8927 | C20: =C18+C19 -> 7903 | D20: =D18+D19 -> 7961 | E20: =E18+E19 -> 7961 | F20: =F18+F19 -> 7961 | G20: =G18+G19 -> 7961 | H20: =H18+H19 -> 7961 | I20: =I18+I19 -> 7961
A22: Historical 'Other' and debt-schedule lines are back-solved plugs that reconcile the schedule to actual reported balances (FX translation, disposals and other non-capex PP&E movements are not separately disclosed). Forecast capex and D&A are driven by the Assumptions tab as a % of revenue.
